<?xml version="1.0" encoding="UTF-8"?>
<flow id="991264fb-f9db-407e-a01f-2e73b7385a46">
  <descriptionCdata><![CDATA[991264fb-f9db-407e-a01f-2e73b7385a46.19b2665c-49ff-400e-9f74-7b93a5660f90.prompt=Close session?\:
991264fb-f9db-407e-a01f-2e73b7385a46.3c548464-b415-4c5a-9012-86937644c126.description=<pre>Retrieves the power state of virtual machine (poweredOn,poweredOff,suspended).\n\nInputs\:\n    host - VMWare host hostname or IP.\n    user - VMWare username.\n    password - VMWare user's password.\n    port - Port to connect on.\n    protocol - Connection protocol.\nValid values\: "https", "http"    \n    closeSession - Close the internally kept VMware Infrastructure API session at completion of operation.\nValid values\: "true", "false"\n    virtualMachine - Primary Virtual Machine identifier. Inventorypath (Datacenter/vm/Folder/MyVM), Name of VM, IP (IPv4 or IPv6 depending upon ESX version), hostname (full), UUID, or the VM id (vm-123,123).\n    vmIdentifierType - Virtual machine identifier type.\nValid values\: "inventorypath", "name", "ip", "hostname", "uuid", "vmid"    \n\nResponses\:\n    success - The operation completed successfully.\n    failure - Something went wrong.\n\nReturns\:\n    returnResult - Task completion return message.\n    powerState - Power state (poweredOn,poweredOff,suspended).\n\nNotes\:\nInventory Path Formatting\: If host is an ESX server inventory path will be\: ha-datacenter/vm/<name of vm> .  If host is a vCenter the inventory path will be\: <name of datacenter>/vm/<folders>/<name of vm> . The <folders>/<name of vm> part of the path is based on the "Virtual Machines & Templates" view in the vCenter client. The inventory path is case sensitive.\n</pre>
991264fb-f9db-407e-a01f-2e73b7385a46.900f4a44-a1e1-468a-ba61-ad534f808875.prompt=VMWare Host\:
991264fb-f9db-407e-a01f-2e73b7385a46.9907c5ea-a56f-4372-951c-07d23a866b5f.prompt=Virtual Machine\:
991264fb-f9db-407e-a01f-2e73b7385a46.ebc1286a-15e3-43c0-89d8-61bc2b4f350a.prompt=Password\:
991264fb-f9db-407e-a01f-2e73b7385a46.f7c20528-5ec3-4336-87ba-fe0fcd03a425.prompt=Identify VM by\:
]]></descriptionCdata>
  <annotation></annotation>
  <name>Check for running VMs</name>
  <categories/>
  <inputs/>
  <possibleResponses/>
  <availableResultExpressions/>
  <resultExpression id="4d3580b0-b5c3-4bf9-be40-6d8eb1afce1f">
    <annotation></annotation>
    <name>FailureMessage</name>
    <fieldName>FailureMessage</fieldName>
    <sourceType>RAWRESULT</sourceType>
    <filters/>
  </resultExpression>
  <iconSpec id="7e63a817-0a67-4de1-ab6e-48aee6454409">
    <baseIcon>flow.png</baseIcon>
    <basePath>System</basePath>
    <readOnly>false</readOnly>
    <layers/>
  </iconSpec>
  <callouts/>
  <checkPointFlow>true</checkPointFlow>
  <compatibleRuntimeContext>false</compatibleRuntimeContext>
  <historyCheckPointFlow>true</historyCheckPointFlow>
  <steps>
    <step id="3c548464-b415-4c5a-9012-86937644c126">
      <annotation>991264fb-f9db-407e-a01f-2e73b7385a46.3c548464-b415-4c5a-9012-86937644c126.description</annotation>
      <name>Get Power State</name>
      <bounds>
        <x>150.0</x>
        <y>270.0</y>
      </bounds>
      <layer>-1</layer>
      <hideInbound>false</hideInbound>
      <addResultToRunContext>false</addResultToRunContext>
      <isCriticalStep>false</isCriticalStep>
      <isNonBlocking>false</isNonBlocking>
      <isParallelStep>false</isParallelStep>
      <isSingleResponse>false</isSingleResponse>
      <recordInHistory>false</recordInHistory>
      <recordRawOutput>true</recordRawOutput>
      <recordPrimaryOutput>true</recordPrimaryOutput>
      <checkPointStep>true</checkPointStep>
      <historyCheckPointStep>true</historyCheckPointStep>
      <scriptResultStep>false</scriptResultStep>
      <userPrompt></userPrompt>
      <bindings>
        <userInputBinding id="900f4a44-a1e1-468a-ba61-ad534f808875">
          <annotation></annotation>
          <toContextKey></toContextKey>
          <fromContextKey></fromContextKey>
          <assignFromContext>false</assignFromContext>
          <assignToContext>true</assignToContext>
          <inputType>STRING</inputType>
          <isList>false</isList>
          <required>true</required>
          <isPersisted>true</isPersisted>
          <inputSymbol>host</inputSymbol>
          <listDelimiter>,</listDelimiter>
          <record>false</record>
          <prompt>991264fb-f9db-407e-a01f-2e73b7385a46.900f4a44-a1e1-468a-ba61-ad534f808875.prompt</prompt>
          <isMultiSelect>false</isMultiSelect>
          <sourceDelimiter>|</sourceDelimiter>
        </userInputBinding>
        <staticBinding id="46cd030e-f679-4a29-bf3e-521839c50711">
          <annotation></annotation>
          <toContextKey></toContextKey>
          <fromContextKey></fromContextKey>
          <assignFromContext>false</assignFromContext>
          <assignToContext>true</assignToContext>
          <inputType>STRING</inputType>
          <isList>false</isList>
          <required>false</required>
          <isPersisted>true</isPersisted>
          <inputSymbol>user</inputSymbol>
          <listDelimiter>,</listDelimiter>
          <record>false</record>
        </staticBinding>
        <userInputBinding id="ebc1286a-15e3-43c0-89d8-61bc2b4f350a">
          <annotation></annotation>
          <toContextKey></toContextKey>
          <fromContextKey></fromContextKey>
          <assignFromContext>false</assignFromContext>
          <assignToContext>true</assignToContext>
          <inputType>ENCRYPTED</inputType>
          <recordKey></recordKey>
          <isList>false</isList>
          <required>true</required>
          <isPersisted>false</isPersisted>
          <inputSymbol>password</inputSymbol>
          <listDelimiter>,</listDelimiter>
          <record>false</record>
          <prompt>991264fb-f9db-407e-a01f-2e73b7385a46.ebc1286a-15e3-43c0-89d8-61bc2b4f350a.prompt</prompt>
          <isMultiSelect>false</isMultiSelect>
          <sourceDelimiter>|</sourceDelimiter>
        </userInputBinding>
        <staticBinding id="e2724113-6641-4a5e-916f-488645d309df">
          <annotation></annotation>
          <toContextKey></toContextKey>
          <fromContextKey></fromContextKey>
          <assignFromContext>false</assignFromContext>
          <assignToContext>true</assignToContext>
          <inputType>STRING</inputType>
          <isList>false</isList>
          <required>true</required>
          <isPersisted>true</isPersisted>
          <inputSymbol>port</inputSymbol>
          <listDelimiter>,</listDelimiter>
          <value>443</value>
          <record>false</record>
        </staticBinding>
        <staticBinding id="bbad8054-25c5-4e97-bd4e-0bea5a18a3f7">
          <annotation></annotation>
          <toContextKey></toContextKey>
          <fromContextKey></fromContextKey>
          <assignFromContext>false</assignFromContext>
          <assignToContext>true</assignToContext>
          <inputType>STRING</inputType>
          <isList>false</isList>
          <required>true</required>
          <isPersisted>true</isPersisted>
          <inputSymbol>protocol</inputSymbol>
          <listDelimiter>,</listDelimiter>
          <value>https</value>
          <record>false</record>
        </staticBinding>
        <userInputBinding id="f7c20528-5ec3-4336-87ba-fe0fcd03a425">
          <annotation></annotation>
          <toContextKey></toContextKey>
          <fromContextKey></fromContextKey>
          <assignFromContext>false</assignFromContext>
          <assignToContext>true</assignToContext>
          <inputType>STRING</inputType>
          <isList>false</isList>
          <required>true</required>
          <isPersisted>true</isPersisted>
          <inputSymbol>vmIdentifierType</inputSymbol>
          <listDelimiter>,</listDelimiter>
          <record>false</record>
          <prompt>991264fb-f9db-407e-a01f-2e73b7385a46.f7c20528-5ec3-4336-87ba-fe0fcd03a425.prompt</prompt>
          <isMultiSelect>false</isMultiSelect>
          <link>
            <refId>30d93841-3dba-4f85-a25d-425d36161504</refId>
            <refName>VMReferenceType</refName>
          </link>
          <sourceDelimiter>|</sourceDelimiter>
        </userInputBinding>
        <userInputBinding id="9907c5ea-a56f-4372-951c-07d23a866b5f">
          <annotation></annotation>
          <toContextKey></toContextKey>
          <fromContextKey></fromContextKey>
          <assignFromContext>false</assignFromContext>
          <assignToContext>true</assignToContext>
          <inputType>STRING</inputType>
          <isList>false</isList>
          <required>true</required>
          <isPersisted>true</isPersisted>
          <inputSymbol>virtualMachine</inputSymbol>
          <listDelimiter>,</listDelimiter>
          <record>false</record>
          <prompt>991264fb-f9db-407e-a01f-2e73b7385a46.9907c5ea-a56f-4372-951c-07d23a866b5f.prompt</prompt>
          <isMultiSelect>false</isMultiSelect>
          <sourceDelimiter>|</sourceDelimiter>
        </userInputBinding>
        <userInputBinding id="19b2665c-49ff-400e-9f74-7b93a5660f90">
          <annotation></annotation>
          <assignFromContext>false</assignFromContext>
          <assignToContext>true</assignToContext>
          <inputType>STRING</inputType>
          <isList>false</isList>
          <required>false</required>
          <isPersisted>true</isPersisted>
          <inputSymbol>closeSession</inputSymbol>
          <listDelimiter>,</listDelimiter>
          <record>false</record>
          <prompt>991264fb-f9db-407e-a01f-2e73b7385a46.19b2665c-49ff-400e-9f74-7b93a5660f90.prompt</prompt>
          <isMultiSelect>false</isMultiSelect>
          <link>
            <refId>96a1ed25-cdc9-4ff6-8fba-e9c044c5ca53</refId>
            <refName>Boolean - False Default</refName>
          </link>
          <sourceDelimiter>|</sourceDelimiter>
        </userInputBinding>
      </bindings>
      <transitions/>
      <properties/>
      <opRef>
        <refId>4e6bdb7c-17ca-4132-9cae-b0f0f10476c4</refId>
      </opRef>
      <assignments/>
      <throttleSize>0</throttleSize>
    </step>
  </steps>
</flow>